langchain_voyageai-0.3.1.dist-info/METADATA
langchain_voyageai-0.3.1.dist-info/WHEEL
langchain_voyageai-0.3.1.dist-info/entry_points.txt
langchain_voyageai-0.3.1.dist-info/licenses/LICENSE
langchain_voyageai/__init__.py
langchain_voyageai/embeddings.py
langchain_voyageai/py.typed
langchain_voyageai/rerank.py
langchain_voyageai-0.3.1.dist-info/RECORD
