Metadata-Version: 2.1
Name: langchain-voyageai
Version: 0.3.1
Summary: An integration package connecting VoyageAI and LangChain
License: MIT
Project-URL: Source Code, https://github.com/langchain-ai/langchain/tree/master/libs/partners/voyageai
Project-URL: Release Notes, https://github.com/langchain-ai/langchain/releases?q=tag%3A%22langchain-voyageai%3D%3D0%22&expanded=true
Project-URL: repository, https://github.com/langchain-ai/langchain
Requires-Python: <=3.13,>=3.10
Requires-Dist: langchain-core>=1.0.0
Requires-Dist: voyageai<1,>=0.3.7
Requires-Dist: pydantic<3,>=2
